{"45-3-1": {"is_checked": true, "mouth": ["shifted", "default"], "eyebrows": ["default"], "nostrils": ["default"], "emotion": "\u043e\u0442\u0432\u0440\u0430\u0449\u0435\u043d\u0438\u0435", "cheeks": ["default"], "eyes": ["default"]}, "30-3-1": {"is_checked": true, "mouth": ["open"], "eyebrows": ["default"], "nostrils": ["default"], "emotion": "\u043e\u0442\u0432\u0440\u0430\u0449\u0435\u043d\u0438\u0435", "cheeks": ["default"], "eyes": ["default"]}, "51-4-1": {"is_checked": true, "mouth": ["(undef)"], "eyebrows": ["default"], "nostrils": ["(undef)"], "emotion": "\u043e\u0442\u0432\u0440\u0430\u0449\u0435\u043d\u0438\u0435", "cheeks": ["default"], "eyes": ["default"]}, "30-3-2": {"is_checked": true, "mouth": ["open"], "eyebrows": ["default"], "nostrils": ["up"], "emotion": "\u043e\u0442\u0432\u0440\u0430\u0449\u0435\u043d\u0438\u0435", "cheeks": ["default", "up"], "eyes": ["default"]}}