{"63-2-1": {"is_checked": true, "mouth": ["smile"], "eyebrows": ["default"], "nostrils": ["up"], "emotion": "\u0443\u043b\u044b\u0431\u043a\u0430", "cheeks": ["default", "up"], "eyes": ["default"]}, "47-2-1": {"is_checked": true, "mouth": ["smile"], "eyebrows": ["default"], "nostrils": ["default"], "emotion": "\u0443\u043b\u044b\u0431\u043a\u0430", "cheeks": ["up"], "eyes": ["default"]}, "49-4-1": {"is_checked": true, "mouth": ["smile"], "eyebrows": ["default"], "nostrils": ["default"], "emotion": "\u0443\u043b\u044b\u0431\u043a\u0430", "cheeks": ["up"], "eyes": ["default"]}, "54-5-1": {"is_checked": true, "mouth": ["smile"], "eyebrows": ["default"], "nostrils": ["default"], "emotion": "\u0443\u043b\u044b\u0431\u043a\u0430", "cheeks": ["default", "up"], "eyes": ["closed"]}, "47-3-2": {"is_checked": true, "mouth": ["smile"], "eyebrows": ["default"], "nostrils": ["up", "default"], "emotion": "\u0443\u043b\u044b\u0431\u043a\u0430", "cheeks": ["up"], "eyes": ["default"]}, "63-1-1": {"is_checked": true, "mouth": ["smile"], "eyebrows": ["default"], "nostrils": ["default"], "emotion": "\u0443\u043b\u044b\u0431\u043a\u0430", "cheeks": ["default", "up"], "eyes": ["default"]}, "63-2-2": {"is_checked": true, "mouth": ["smile"], "eyebrows": ["default"], "nostrils": ["default"], "emotion": "\u0443\u043b\u044b\u0431\u043a\u0430", "cheeks": ["default", "up"], "eyes": ["default"]}, "47-2-2": {"is_checked": true, "mouth": ["smile"], "eyebrows": ["default"], "nostrils": ["default"], "emotion": "\u0443\u043b\u044b\u0431\u043a\u0430", "cheeks": ["default"], "eyes": ["default"]}, "64-2-1": {"is_checked": true, "mouth": ["smile"], "eyebrows": ["default"], "nostrils": ["up", "default"], "emotion": "\u0443\u043b\u044b\u0431\u043a\u0430", "cheeks": ["default", "up"], "eyes": ["default"]}, "47-1-1": {"is_checked": true, "mouth": ["smile"], "eyebrows": ["default"], "nostrils": ["default"], "emotion": "\u0443\u043b\u044b\u0431\u043a\u0430", "cheeks": ["up"], "eyes": ["default"]}, "56-2-2": {"is_checked": true, "mouth": ["smile"], "eyebrows": ["default"], "nostrils": ["up"], "emotion": "\u0443\u043b\u044b\u0431\u043a\u0430", "cheeks": ["up"], "eyes": ["default"]}, "47-3-1": {"is_checked": true, "mouth": ["smile"], "eyebrows": ["default"], "nostrils": ["default"], "emotion": "\u0443\u043b\u044b\u0431\u043a\u0430", "cheeks": ["up"], "eyes": ["default"]}, "56-2-1": {"is_checked": true, "mouth": ["smile"], "eyebrows": ["default"], "nostrils": ["default"], "emotion": "\u0443\u043b\u044b\u0431\u043a\u0430", "cheeks": ["default", "up"], "eyes": ["default"]}, "65-2-2": {"is_checked": true, "mouth": ["smile"], "eyebrows": ["default"], "nostrils": ["default"], "emotion": "\u0443\u043b\u044b\u0431\u043a\u0430", "cheeks": ["up"], "eyes": ["default"]}, "49-1-2": {"is_checked": true, "mouth": ["smile"], "eyebrows": ["(undef)"], "nostrils": ["default"], "emotion": "\u0443\u043b\u044b\u0431\u043a\u0430", "cheeks": ["up"], "eyes": ["(undef)"]}, "41-1-1": {"is_checked": true, "mouth": ["smile"], "eyebrows": ["up"], "nostrils": ["up"], "emotion": "\u0443\u043b\u044b\u0431\u043a\u0430", "cheeks": ["up"], "eyes": ["default"]}, "31-2-2": {"is_checked": true, "mouth": ["smile"], "eyebrows": ["default"], "nostrils": ["default"], "emotion": "\u0443\u043b\u044b\u0431\u043a\u0430", "cheeks": ["default", "up"], "eyes": ["(undef)"]}, "56-4-1": {"is_checked": true, "mouth": ["smile"], "eyebrows": ["default"], "nostrils": ["default"], "emotion": "\u0443\u043b\u044b\u0431\u043a\u0430", "cheeks": ["default", "up"], "eyes": ["default"]}, "37-1-2": {"is_checked": true, "mouth": ["smile"], "eyebrows": ["default"], "nostrils": ["default"], "emotion": "\u0443\u043b\u044b\u0431\u043a\u0430", "cheeks": ["up"], "eyes": ["closed"]}, "41-1-2": {"is_checked": true, "mouth": ["smile"], "eyebrows": ["default"], "nostrils": ["up"], "emotion": "\u0443\u043b\u044b\u0431\u043a\u0430", "cheeks": ["up"], "eyes": ["default"]}, "56-1-1": {"is_checked": true, "mouth": ["smile"], "eyebrows": ["default"], "nostrils": ["up"], "emotion": "\u0443\u043b\u044b\u0431\u043a\u0430", "cheeks": ["default", "up"], "eyes": ["default"]}, "64-3-1": {"is_checked": true, "mouth": ["open", "smile"], "eyebrows": ["default"], "nostrils": ["default"], "emotion": "\u0443\u043b\u044b\u0431\u043a\u0430", "cheeks": ["default", "up"], "eyes": ["default"]}, "31-3-1": {"is_checked": true, "mouth": ["smile"], "eyebrows": ["default"], "nostrils": ["default"], "emotion": "\u0443\u043b\u044b\u0431\u043a\u0430", "cheeks": ["up"], "eyes": ["default"]}, "64-4-1": {"is_checked": true, "mouth": ["smile"], "eyebrows": ["default"], "nostrils": ["up"], "emotion": "\u0443\u043b\u044b\u0431\u043a\u0430", "cheeks": ["default", "up"], "eyes": ["default"]}, "32-1-1": {"is_checked": true, "mouth": ["open", "smile"], "eyebrows": ["up"], "nostrils": ["up", "default"], "emotion": "\u0443\u043b\u044b\u0431\u043a\u0430", "cheeks": ["default", "up"], "eyes": ["default"]}, "64-1-1": {"is_checked": true, "mouth": ["smile"], "eyebrows": ["default"], "nostrils": ["default"], "emotion": "\u0443\u043b\u044b\u0431\u043a\u0430", "cheeks": ["default", "up"], "eyes": ["default"]}, "47-1-2": {"is_checked": true, "mouth": ["smile"], "eyebrows": ["default"], "nostrils": ["default"], "emotion": "\u0443\u043b\u044b\u0431\u043a\u0430", "cheeks": ["default"], "eyes": ["default"]}, "38-2-1": {"is_checked": true, "mouth": ["smile"], "eyebrows": ["default"], "nostrils": ["up", "default"], "emotion": "\u0443\u043b\u044b\u0431\u043a\u0430", "cheeks": ["up"], "eyes": ["(undef)"]}, "47-4-2": {"is_checked": true, "mouth": ["smile"], "eyebrows": ["default"], "nostrils": ["default"], "emotion": "\u0443\u043b\u044b\u0431\u043a\u0430", "cheeks": ["up"], "eyes": ["(undef)"]}, "65-2-1": {"is_checked": true, "mouth": ["smile"], "eyebrows": ["default"], "nostrils": ["default"], "emotion": "\u0443\u043b\u044b\u0431\u043a\u0430", "cheeks": ["default", "up"], "eyes": ["default"]}, "49-2-1": {"is_checked": true, "mouth": ["smile"], "eyebrows": ["up"], "nostrils": ["up", "default"], "emotion": "\u0443\u043b\u044b\u0431\u043a\u0430", "cheeks": ["up"], "eyes": ["(undef)"]}, "49-1-1": {"is_checked": true, "mouth": ["smile"], "eyebrows": ["up"], "nostrils": ["up"], "emotion": "\u0443\u043b\u044b\u0431\u043a\u0430", "cheeks": ["up"], "eyes": ["default"]}, "49-2-2": {"is_checked": true, "mouth": ["open", "smile"], "eyebrows": ["default"], "nostrils": ["default"], "emotion": "\u0443\u043b\u044b\u0431\u043a\u0430", "cheeks": ["up"], "eyes": ["(undef)"]}, "41-2-1": {"is_checked": true, "mouth": ["smile"], "eyebrows": ["default"], "nostrils": ["default"], "emotion": "\u0443\u043b\u044b\u0431\u043a\u0430", "cheeks": ["up"], "eyes": ["default"]}, "37-1-1": {"is_checked": true, "mouth": ["smile"], "eyebrows": ["default"], "nostrils": ["(undef)", "default"], "emotion": "\u0443\u043b\u044b\u0431\u043a\u0430", "cheeks": ["default"], "eyes": ["closed"]}, "56-4-2": {"is_checked": true, "mouth": ["smile"], "eyebrows": ["default"], "nostrils": ["default"], "emotion": "\u0443\u043b\u044b\u0431\u043a\u0430", "cheeks": ["default", "up"], "eyes": ["default"]}, "32-3-1": {"is_checked": true, "mouth": ["open", "smile"], "eyebrows": ["default"], "nostrils": ["up", "default"], "emotion": "\u0443\u043b\u044b\u0431\u043a\u0430", "cheeks": ["up"], "eyes": ["default"]}, "51-3-1": {"is_checked": true, "mouth": ["smile"], "eyebrows": ["default"], "nostrils": ["default"], "emotion": "\u0443\u043b\u044b\u0431\u043a\u0430", "cheeks": ["up", "default"], "eyes": ["default"]}}